del_fem-0.1.1.dist-info/METADATA
del_fem-0.1.1.dist-info/WHEEL
del_fem-0.1.1.dist-info/license_files/LICENSE
del_fem/LaplacianMatrix.py
del_fem/MassMatrix.py
del_fem/__init__.py
del_fem/Arap.py
del_fem/Mitc3.py
del_fem/LinearSolid.py
del_fem/del_fem.cpython-37m-darwin.so
del_fem-0.1.1.dist-info/RECORD
