Metadata-Version: 2.1
Name: del-fem
Version: 0.1.1
Classifier: Programming Language :: Rust
Classifier: Programming Language :: Python :: Implementation :: CPython
Classifier: Programming Language :: Python :: Implementation :: PyPy
Requires-Dist: numpy
Requires-Dist: scipy
Requires-Dist: del-msh
License-File: LICENSE
Requires-Python: >=3.7
